{
    "swagger": "2.0",
    "info": {
        "contact": {}
    },
    "paths": {
        "/v1/email/client_send": {
            "post": {
                "description": "get the status of server.",
                "consumes": [
                    "*/*"
                ],
                "produces": [
                    "application/json"
                ],
                "tags": [
                    "root"
                ],
                "summary": "Show the status of server.",
                "parameters": [
                    {
                        "type": "string",
                        "description": "NameEmailReceive",
                        "name": "NameEmailReceive",
                        "in": "query",
                        "required": true
                    },
                    {
                        "type": "string",
                        "description": "SubjectEmail",
                        "name": "SubjectEmail",
                        "in": "query",
                        "required": true
                    },
                    {
                        "type": "string",
                        "description": "Content",
                        "name": "Content",
                        "in": "query",
                        "required": true
                    }
                ],
                "responses": {
                    "200": {
                        "description": "OK",
                        "schema": {
                            "type": "object",
                            "additionalProperties": true
                        }
                    }
                }
            }
        }
    }
}